<?xml version="1.0" encoding="UTF-8"?>

<!-- pressures/traction in MPa -->

<Materials>
  <Solid cellTags = "1" name = "rock">

    <Constitutive>
      <Elastic
               youngModulus = "4900.0"
               poissonRatio = "0.25"
               />
    </Constitutive>

  </Solid>

  <Solid cellTags = "2" name = "clay">

    <Constitutive>
      <Elastic
               youngModulus = "30.0"
               poissonRatio = "0.25"
               />
    </Constitutive>
  </Solid>


  <Solid cellTags = "3" name = "sand">

    <Constitutive>
      <Elastic
               youngModulus = "40.0"
               poissonRatio = "0.25"
               />
    </Constitutive>
  </Solid>

</Materials>